download/__init__.py
download/download.py
download-0.3.5.dist-info/LICENSE
download-0.3.5.dist-info/METADATA
download-0.3.5.dist-info/WHEEL
download-0.3.5.dist-info/top_level.txt
download-0.3.5.dist-info/RECORD
