Metadata-Version: 2.1
Name: download
Version: 0.3.5
Summary: A quick module to help downloading files using python.
Home-page: https://github.com/choldgraf/download
Maintainer: Chris Holdgraf
Maintainer-email: choldgraf@gmail.com
License: BSD (3-clause)
Download-URL: https://github.com/choldgraf/download
Platform: any
Classifier: Intended Audience :: Science/Research
Classifier: Intended Audience :: Developers
Classifier: License :: OSI Approved
Classifier: Programming Language :: Python
Classifier: Topic :: Software Development
Classifier: Topic :: Scientific/Engineering
Provides-Extra: dev
Provides-Extra: sphinx
